<!-- win7x86-64 sampled -->
<domain type='kvm'>
  <name>%(Name)s</name>
  <uuid>%(UUID)s</uuid>
  <memory unit='KiB'>%(MEM)s</memory>
  <currentMemory unit='KiB'>%(MEM)s</currentMemory>
  <vcpu placement='static'>1</vcpu>
  <resource>
    <partition>/machine</partition>
  </resource>
  <os>
    <type arch='x86_64' machine='pc-i440fx-rhel7.2.0'>hvm</type>
    <boot dev='hd'/>
  </os>
  <features>
    <acpi/>
    <apic/>
    <hyperv>
      <relaxed state='on'/>
      <vapic state='on'/>
      <spinlocks state='on' retries='8191'/>
    </hyperv>
  </features>
  <cpu mode='custom' match='exact'>
    <model fallback='allow'>Haswell-noTSX</model>
  </cpu>
  <clock offset='localtime'>
    <timer name='rtc' tickpolicy='catchup'/>
    <timer name='pit' tickpolicy='delay'/>
    <timer name='hpet' present='no'/>
    <timer name='hypervclock' present='yes'/>
  </clock>
  <on_poweroff>destroy</on_poweroff>
  <on_reboot>restart</on_reboot>
  <on_crash>restart</on_crash>
  <pm>
    <suspend-to-mem enabled='no'/>
    <suspend-to-disk enabled='no'/>
  </pm>
  <devices>
    <emulator>/usr/libexec/qemu-kvm</emulator>
    <disk type='file' device='disk'>
      <driver name='qemu' type='qcow2'/>
      <source file='%(Image)s'/>
      <backingStore/>
      <target dev='hda' bus='ide'/>
    </disk>
    <interface type='network'>
      <mac address='%(MAC)s'/>
      <source network='%(Net)s'/>
      <model type='rtl8139'/>
    </interface>
    <input type='mouse' bus='ps2'/>
    <input type='keyboard' bus='ps2'/>
    <graphics type='vnc' port='%(VNCPORT)s' autoport='%(VNCAUTO)s' listen='0.0.0.0' passwd='%(VNCPW)s'>
      <listen type='address' address='0.0.0.0'/>
    </graphics>
  </devices>
</domain>
